isimip_client/__init__.py
isimip_client/client.py
isimip_client-1.0.1.dist-info/LICENSE
isimip_client-1.0.1.dist-info/METADATA
isimip_client-1.0.1.dist-info/WHEEL
isimip_client-1.0.1.dist-info/top_level.txt
isimip_client-1.0.1.dist-info/RECORD
