Metadata-Version: 2.1
Name: isimip-client
Version: 1.0.1
Summary: A thin client library to use the API of the ISIMIP repository using Python.
Author-email: Jochen Klar <jochen.klar@pik-potsdam.de>
Maintainer-email: Jochen Klar <jochen.klar@pik-potsdam.de>
License: MIT License
Project-URL: Repository, https://github.com/ISI-MIP/isimip-client
Classifier: Operating System :: OS Independent
Classifier: License :: OSI Approved :: MIT License
Classifier: Programming Language :: Python :: 3.8
Classifier: Programming Language :: Python :: 3.9
Classifier: Programming Language :: Python :: 3.10
Classifier: Programming Language :: Python :: 3.11
Requires-Python: >=3.8
License-File: LICENSE
Requires-Dist: requests >=2
Provides-Extra: jupyter
Requires-Dist: jupyter ; extra == 'jupyter'
Requires-Dist: jupyterlab ; extra == 'jupyter'
Requires-Dist: matplotlib ; extra == 'jupyter'
Requires-Dist: netCDF4 ; extra == 'jupyter'
Requires-Dist: pandas ; extra == 'jupyter'
